{
	"PTF11dij":{
		"name":"PTF11dij",
		"sources":[
			{
				"bibcode":"2017arXiv170801623D",
				"alias":"1"
			}
		],
		"alias":[
			{
				"value":"PTF11dij",
				"source":"1"
			}
		],
		"photometry":[
			{
				"time":"55652.370",
				"band":"r",
				"e_magnitude":"0.06",
				"telescope":"P48",
				"magnitude":"20.01",
				"system":"AB",
				"u_time":"MJD",
				"source":"1"
			},
			{
				"time":"55652.429",
				"band":"r",
				"e_magnitude":"0.06",
				"telescope":"P48",
				"magnitude":"19.85",
				"system":"AB",
				"u_time":"MJD",
				"source":"1"
			},
			{
				"time":"55666.197",
				"band":"r",
				"e_magnitude":"0.03",
				"telescope":"P48",
				"magnitude":"18.08",
				"system":"AB",
				"u_time":"MJD",
				"source":"1"
			},
			{
				"time":"55666.240",
				"band":"r",
				"e_magnitude":"0.02",
				"telescope":"P48",
				"magnitude":"18.04",
				"system":"AB",
				"u_time":"MJD",
				"source":"1"
			},
			{
				"time":"55694.324",
				"band":"r",
				"e_magnitude":"0.01",
				"telescope":"P60",
				"magnitude":"17.95",
				"system":"AB",
				"u_time":"MJD",
				"source":"1"
			},
			{
				"time":"55694.327",
				"band":"g",
				"e_magnitude":"0.01",
				"telescope":"P60",
				"magnitude":"17.83",
				"system":"AB",
				"u_time":"MJD",
				"source":"1"
			},
			{
				"time":"55694.329",
				"band":"i",
				"e_magnitude":"0.01",
				"telescope":"P60",
				"magnitude":"18.05",
				"system":"AB",
				"u_time":"MJD",
				"source":"1"
			},
			{
				"time":"55694.330",
				"band":"r",
				"e_magnitude":"0.01",
				"telescope":"P60",
				"magnitude":"17.90",
				"system":"AB",
				"u_time":"MJD",
				"source":"1"
			},
			{
				"time":"55694.334",
				"band":"g",
				"e_magnitude":"0.01",
				"telescope":"P60",
				"magnitude":"17.98",
				"system":"AB",
				"u_time":"MJD",
				"source":"1"
			},
			{
				"time":"55695.205",
				"band":"r",
				"e_magnitude":"0.03",
				"telescope":"P48",
				"magnitude":"17.89",
				"system":"AB",
				"u_time":"MJD",
				"source":"1"
			},
			{
				"time":"55695.249",
				"band":"r",
				"e_magnitude":"0.02",
				"telescope":"P48",
				"magnitude":"17.96",
				"system":"AB",
				"u_time":"MJD",
				"source":"1"
			},
			{
				"time":"55708.423",
				"band":"i",
				"e_magnitude":"0.04",
				"telescope":"P60",
				"magnitude":"18.42",
				"system":"AB",
				"u_time":"MJD",
				"source":"1"
			},
			{
				"time":"55708.425",
				"band":"r",
				"e_magnitude":"0.03",
				"telescope":"P60",
				"magnitude":"18.42",
				"system":"AB",
				"u_time":"MJD",
				"source":"1"
			},
			{
				"time":"55713.378",
				"band":"g",
				"e_magnitude":"0.06",
				"telescope":"P60",
				"magnitude":"18.88",
				"system":"AB",
				"u_time":"MJD",
				"source":"1"
			},
			{
				"time":"55744.294",
				"band":"i",
				"e_magnitude":"0.09",
				"telescope":"P60",
				"magnitude":"20.32",
				"system":"AB",
				"u_time":"MJD",
				"source":"1"
			},
			{
				"time":"55744.296",
				"band":"r",
				"e_magnitude":"0.10",
				"telescope":"P60",
				"magnitude":"20.68",
				"system":"AB",
				"u_time":"MJD",
				"source":"1"
			},
			{
				"time":"55744.299",
				"band":"g",
				"e_magnitude":"0.15",
				"telescope":"P60",
				"magnitude":"21.30",
				"system":"AB",
				"u_time":"MJD",
				"source":"1"
			},
			{
				"time":"55754.299",
				"band":"i",
				"e_magnitude":"0.12",
				"telescope":"P60",
				"magnitude":"21.02",
				"system":"AB",
				"u_time":"MJD",
				"source":"1"
			},
			{
				"time":"55754.301",
				"band":"r",
				"e_magnitude":"0.14",
				"telescope":"P60",
				"magnitude":"21.55",
				"system":"AB",
				"u_time":"MJD",
				"source":"1"
			},
			{
				"time":"55755.301",
				"band":"i",
				"e_magnitude":"0.12",
				"telescope":"P60",
				"magnitude":"20.68",
				"system":"AB",
				"u_time":"MJD",
				"source":"1"
			},
			{
				"time":"55766.273",
				"band":"i",
				"e_magnitude":"0.19",
				"telescope":"P60",
				"magnitude":"21.00",
				"system":"AB",
				"u_time":"MJD",
				"source":"1"
			},
			{
				"time":"55779.196",
				"band":"i",
				"e_magnitude":"0.19",
				"telescope":"P60",
				"magnitude":"21.72",
				"system":"AB",
				"u_time":"MJD",
				"source":"1"
			}
		]
	}
}
