{
	"SN2008ip":{
		"name":"SN2008ip",
		"sources":[
			{
				"bibcode":"2011ApJ...741....7F",
				"alias":"1"
			}
		],
		"alias":[
			{
				"value":"SN2008ip",
				"source":"1"
			}
		],
		"claimedtype":[
			{
				"value":"IIn",
				"source":"1"
			}
		],
		"photometry":[
			{
				"time":"55088",
				"band":"I1",
				"e_magnitude":"0.65",
				"instrument":"IRAC",
				"magnitude":"16.87",
				"telescope":"Spitzer",
				"u_time":"MJD",
				"source":"1"
			},
			{
				"time":"55088",
				"band":"I2",
				"e_magnitude":"0.46",
				"instrument":"IRAC",
				"magnitude":"16.03",
				"telescope":"Spitzer",
				"u_time":"MJD",
				"source":"1"
			}
		]
	}
}
